docs/source/conf.py
docs/source/developer_docs/example_code/RandomDataPlot.py
docs/source/developer_docs/example_code/SillyClassifier.py
docs/source/developer_docs/example_code/SillyEncoder.py
docs/source/developer_docs/example_code/SillyFilter.py
docs/source/developer_docs/example_code/_test_randomDataPlot.py
docs/source/developer_docs/example_code/_test_sillyClassifier.py
docs/source/developer_docs/example_code/_test_sillyEncoder.py
docs/source/developer_docs/example_code/_test_sillyFilter.py
immuneML/__init__.py
immuneML/IO/__init__.py
immuneML/IO/dataset_export/AIRRExporter.py
immuneML/IO/dataset_export/DataExporter.py
immuneML/IO/dataset_export/__init__.py
immuneML/IO/dataset_import/AIRRImport.py
immuneML/IO/dataset_import/DataImport.py
immuneML/IO/dataset_import/DatasetImportParams.py
immuneML/IO/dataset_import/GenericImport.py
immuneML/IO/dataset_import/IGoRImport.py
immuneML/IO/dataset_import/IReceptorImport.py
immuneML/IO/dataset_import/ImmunoSEQRearrangementImport.py
immuneML/IO/dataset_import/ImmunoSEQSampleImport.py
immuneML/IO/dataset_import/MiXCRImport.py
immuneML/IO/dataset_import/OLGAImport.py
immuneML/IO/dataset_import/RandomReceptorDatasetImport.py
immuneML/IO/dataset_import/RandomRepertoireDatasetImport.py
immuneML/IO/dataset_import/RandomSequenceDatasetImport.py
immuneML/IO/dataset_import/TenxGenomicsImport.py
immuneML/IO/dataset_import/VDJdbImport.py
immuneML/IO/dataset_import/__init__.py
immuneML/IO/dataset_import/conversion/imgt_adaptive_conversion.csv
immuneML/IO/ml_method/MLExporter.py
immuneML/IO/ml_method/MLImport.py
immuneML/IO/ml_method/MLMethodConfiguration.py
immuneML/IO/ml_method/UtilIO.py
immuneML/IO/ml_method/__init__.py
immuneML/analysis/SequenceMatcher.py
immuneML/analysis/__init__.py
immuneML/analysis/criteria_matches/BooleanType.py
immuneML/analysis/criteria_matches/CriteriaMatcher.py
immuneML/analysis/criteria_matches/CriteriaTypeInstantiator.py
immuneML/analysis/criteria_matches/OperationType.py
immuneml-3.0.17.dist-info/licenses/LICENSE.md
immuneml-3.0.17.dist-info/METADATA
immuneml-3.0.17.dist-info/WHEEL
immuneml-3.0.17.dist-info/entry_points.txt
immuneml-3.0.17.dist-info/top_level.txt
immuneml-3.0.17.dist-info/RECORD
