Metadata-Version: 2.4
Name: immuneML
Version: 3.0.17
Summary: immuneML is a software platform for machine learning analysis of immune receptor repertoires.
Author-email: immuneML Team <milenpa@uio.no>
License: GNU Affero General Public License v3
Project-URL: Homepage, https://github.com/uio-bmi/immuneML
Classifier: Programming Language :: Python :: 3
Classifier: License :: OSI Approved :: GNU Affero General Public License v3
Requires-Python: >=3.7
License-File: LICENSE.md
Requires-Dist: numpy<=1.26.4
Requires-Dist: pandas>=2.1.0
Requires-Dist: PyYAML>=5.3
Requires-Dist: scikit-learn>=0.23
Requires-Dist: python-glmnet
Requires-Dist: matplotlib>=3.1
Requires-Dist: editdistance
Requires-Dist: regex
Requires-Dist: tzlocal
Requires-Dist: airr>=1.5.1
Requires-Dist: pystache
Requires-Dist: dill>=0.3
Requires-Dist: plotly>=4
Requires-Dist: matplotlib-venn>=0.11
Requires-Dist: scipy<=1.12.0
Requires-Dist: bionumpy>=1.0.12
Requires-Dist: umap-learn
Requires-Dist: olga>=1.2.4
Requires-Dist: psutil
Requires-Dist: kaleido
Requires-Dist: logomaker
Requires-Dist: python-glmnet
Provides-Extra: word2vec
Requires-Dist: gensim>=4; extra == "word2vec"
Provides-Extra: fisher
Requires-Dist: fisher>=0.1.9; extra == "fisher"
Requires-Dist: fishersapi; extra == "fisher"
Provides-Extra: tcrdist
Requires-Dist: tcrdist3>=0.1.6; extra == "tcrdist"
Provides-Extra: gen-models
Requires-Dist: sonnia; extra == "gen-models"
Requires-Dist: torch; extra == "gen-models"
Requires-Dist: transformers; extra == "gen-models"
Requires-Dist: datasets; extra == "gen-models"
Requires-Dist: tokenizers; extra == "gen-models"
Requires-Dist: tensorflow<=2.15.0; extra == "gen-models"
Requires-Dist: accelerate>=0.26.0; extra == "gen-models"
Provides-Extra: embeddings
Requires-Dist: transformers; extra == "embeddings"
Requires-Dist: torch; extra == "embeddings"
Requires-Dist: sentencepiece; extra == "embeddings"
Requires-Dist: esm; extra == "embeddings"
Requires-Dist: httpx; extra == "embeddings"
Provides-Extra: ligo
Requires-Dist: stitchr; extra == "ligo"
Requires-Dist: IMGTgeneDL; extra == "ligo"
Provides-Extra: dl
Requires-Dist: torch; extra == "dl"
Requires-Dist: keras; extra == "dl"
Requires-Dist: tensorflow; extra == "dl"
Requires-Dist: logomaker; extra == "dl"
Requires-Dist: gensim; extra == "dl"
Provides-Extra: all
Requires-Dist: tcrdist3>=0.1.6; extra == "all"
Requires-Dist: sonnia; extra == "all"
Requires-Dist: torch; extra == "all"
Requires-Dist: stitchr; extra == "all"
Requires-Dist: IMGTgeneDL; extra == "all"
Requires-Dist: keras; extra == "all"
Requires-Dist: tensorflow; extra == "all"
Requires-Dist: fisher>=0.1.9; extra == "all"
Requires-Dist: logomaker; extra == "all"
Requires-Dist: fishersapi; extra == "all"
Requires-Dist: gensim>=4; extra == "all"
Requires-Dist: transformers; extra == "all"
Requires-Dist: sentencepiece; extra == "all"
Requires-Dist: httpx; extra == "all"
Requires-Dist: datasets; extra == "all"
Requires-Dist: tokenizers; extra == "all"
Requires-Dist: tensorflow<=2.15.0; extra == "all"
Requires-Dist: accelerate>=0.26.0; extra == "all"
Dynamic: license-file
